README.md
setup.py
pwned/__init__.py
pwned/pwned.py
pwned/utils.py
pywned.egg-info/PKG-INFO
pywned.egg-info/SOURCES.txt
pywned.egg-info/dependency_links.txt
pywned.egg-info/entry_points.txt
pywned.egg-info/not-zip-safe
pywned.egg-info/requires.txt
pywned.egg-info/top_level.txt