Metadata-Version: 1.0
Name: pywned
Version: 0.2.3
Summary: Check if you have an account thathas been compromised in a data breach
Home-page: https://github.com/hudsonbrendon/pwned
Author: Hudson Brendon
Author-email: contato.hudsonbrendon@gmail.com
License: MIT
Platform: UNKNOWN
